{
  "fileId": "269",
  "fileName": "They_Cloned_Tyrone_720p_WEB_DL_HIN_ENG_x264_ESub_Vegamovies_to.mkv",
  "type": "movie",
  "title": "They Cloned Tyrone",
  "originalTitle": "They Cloned Tyrone",
  "overview": "A series of eerie events thrusts an unlikely trio onto the trail of a nefarious government conspiracy lurking directly beneath their neighborhood.",
  "releaseDate": "2023-06-14",
  "year": 2023,
  "runtime": 122,
  "genres": [
    "Comedy",
    "Science Fiction",
    "Mystery"
  ],
  "rating": 6.551,
  "popularity": 3.102,
  "poster": "/data/posters/269.jpg",
  "backdrop": "/data/backdrops/269_bd.jpg",
  "tmdbId": 736769,
  "fetchedAt": "2026-02-15T13:47:58.620Z",
  "needsRetry": false,
  "tv": null
}