{
  "fileId": "498",
  "fileName": "Love_And_Shukla_2017_WebRip_720p_Hindi_AAC_2_0_x264_ESub_Vegamovies.mkv",
  "type": "movie",
  "title": "Love and Shukla",
  "originalTitle": "लव एंड शुक्ला",
  "overview": "Shukla, a newly-married rickshaw driver, struggles to connect with his painfully shy bride Lakshmi. Their woes are compounded by his friends’ bad advice and his family’s inability to understand the concept of personal space.",
  "releaseDate": "2017-10-13",
  "year": 2017,
  "runtime": 117,
  "genres": [
    "Comedy",
    "Drama",
    "Romance"
  ],
  "rating": 7.286,
  "popularity": 0.4332,
  "poster": "/data/posters/498.jpg",
  "backdrop": "/data/backdrops/498_bd.jpg",
  "tmdbId": 486471,
  "fetchedAt": "2026-02-15T13:44:27.136Z",
  "needsRetry": false,
  "tv": null
}