{
  "fileId": "639",
  "fileName": "Panchayat.S01E08.720p.10bit.2CH.x265.HEVC-Vegamovies.is.mkv",
  "type": "tv",
  "title": "Panchayat",
  "originalTitle": "पंचायत",
  "overview": "Panchayat is a comedy-drama, which captures the journey of an engineering graduate Abhishek, who for lack of a better job option joins as secretary of a panchayat office in a remote village of Uttar Pradesh. Stuck between crazy villagers and a difficult village lifestyle Abhishek starts his job with the sole motivation of getting out of there as soon as possible, for which he even prepares for CAT.",
  "releaseDate": "2020-03-05",
  "year": 2020,
  "runtime": 36,
  "genres": [
    "Comedy",
    "Drama"
  ],
  "rating": 8.2,
  "popularity": 6.009,
  "poster": "/data/posters/show_101352.jpg",
  "backdrop": "/data/backdrops/show_101352_bd.jpg",
  "tmdbId": 101352,
  "fetchedAt": "2026-02-15T15:23:20.306Z",
  "needsRetry": false,
  "tv": {
    "showTitle": "Panchayat",
    "originalShowTitle": "पंचायत",
    "seasonNumber": 1,
    "episodeNumber": 8,
    "episodeTitle": "Jab Jaago Tabhi Savera",
    "episodeOverview": "Demotivated by his performance in CAT, Abhishek tries to come at peace with his reality. However, motivation comes to him in the most unexpected way.",
    "showTmdbId": 101352,
    "episodeRuntime": 36,
    "totalSeasons": 5,
    "totalEpisodes": 32
  },
  "audioCodec": "aac",
  "browserPlayable": true
}