{
  "fileId": "989",
  "fileName": "Dhurandhar.The.Revenge.1080p.10Bit.Uncensored-001.mkv",
  "type": "movie",
  "title": "Dhurandhar: The Revenge",
  "originalTitle": "धुरंधर: द रिवेंज",
  "overview": "As rival gangs, corrupt officials and a ruthless Major Iqbal close in, Hamza's mission for his country spirals into a bloody personal war where the line between patriot and monster disappears in the streets of Lyari.",
  "releaseDate": "2026-03-18",
  "year": 2026,
  "runtime": 229,
  "genres": [
    "Action",
    "Crime",
    "Thriller"
  ],
  "rating": 7.359,
  "popularity": 45.5363,
  "awards": "",
  "poster": "/data/posters/989.jpg",
  "backdrop": "/data/backdrops/989_bd.jpg",
  "tmdbId": 1582770,
  "fetchedAt": "2026-05-17T10:04:16.622Z",
  "needsRetry": false,
  "tv": null,
  "audioTracks": [
    {
      "index": 0,
      "streamIndex": 1,
      "codec": "aac",
      "language": "Hindi",
      "languageCode": "hin",
      "title": "VegaMovies.is",
      "channels": 2,
      "channelLayout": "stereo",
      "browserPlayable": true,
      "isDefault": true
    }
  ],
  "audioCodec": "aac",
  "browserPlayable": true,
  "subtitleTracks": [
    {
      "index": 0,
      "streamIndex": 2,
      "codec": "subrip",
      "language": "English",
      "languageCode": "eng",
      "title": "VegaMovies.is",
      "isTextBased": true,
      "isImageBased": false,
      "extractable": true,
      "isDefault": true,
      "isForced": false
    },
    {
      "index": 1,
      "streamIndex": 3,
      "codec": "ass",
      "language": "Hindi",
      "languageCode": "hin",
      "title": "",
      "isTextBased": true,
      "isImageBased": false,
      "extractable": true,
      "isDefault": false,
      "isForced": false
    }
  ],
  "container": "matroska,webm",
  "duration": 9385.578,
  "_tracksDetected": true,
  "_probeFailCount": 0,
  "logo": "/data/logos/989_logo.png",
  "metadataStatus": "COMPLETE",
  "keywords": [
    "undercover",
    "espionage",
    "politics",
    "spy",
    "traitor",
    "patriotism",
    "nationalism",
    "gore",
    "gang leader",
    "pakistan",
    "sequel",
    "betrayal",
    "conspiracy",
    "torture",
    "soldier",
    "india",
    "interrogation",
    "terrorist attack",
    "undercover operation",
    "gun violence",
    "bloodshed",
    "political corruption"
  ],
  "collection": {
    "id": 1628043,
    "name": "Dhurandhar Collection",
    "posterPath": "/r4w2Ps0QN9wzMHDepRoj4H7tAM.jpg",
    "backdropPath": "/4Xv36ZwubtUn6JlIKoKDdhZj565.jpg"
  },
  "watchProviders": {
    "link": "https://www.themoviedb.org/movie/1582770/watch?locale=IN",
    "flatrate": [
      {
        "id": 8,
        "name": "Netflix",
        "logoPath": "/pbpMk2JmcoNnQwx5JGpXngfoWtp.jpg"
      },
      {
        "id": 2336,
        "name": "JioHotstar",
        "logoPath": "/kVqjgpcwvDJOhCupjcLzwwtOp52.jpg"
      }
    ],
    "rent": [],
    "buy": []
  },
  "recommendations": [
    10431,
    126400,
    13054,
    10877,
    250388,
    14362,
    180894,
    484889,
    843633,
    986070,
    455236,
    216580,
    401478,
    9395,
    10596,
    36884,
    45408,
    290729,
    1413976,
    500
  ],
  "similar": [
    1381465,
    13056,
    13123,
    12699,
    12705,
    12711,
    12715,
    449033,
    1005776,
    12651,
    12662,
    12663,
    448887,
    12764,
    12877,
    13008,
    269490,
    12685,
    13183,
    13184
  ]
}